genie_flow_invoker/invoker/ms_sql_server/__init__.py
genie_flow_invoker/invoker/ms_sql_server/manager.py
genie_flow_invoker/invoker/ms_sql_server/model.py
genie_flow_invoker/invoker/ms_sql_server/query.py
genie_flow_invoker/invoker/ms_sql_server/retrieve.py
genie_flow_invoker/invoker/ms_sql_server/store.py
genie_flow_invoker_ms_sql_server-0.7.0a1.dist-info/licenses/NOTICES
genie_flow_invoker_ms_sql_server-0.7.0a1.dist-info/METADATA
genie_flow_invoker_ms_sql_server-0.7.0a1.dist-info/WHEEL
genie_flow_invoker_ms_sql_server-0.7.0a1.dist-info/top_level.txt
genie_flow_invoker_ms_sql_server-0.7.0a1.dist-info/RECORD
